image_processing_clpe/__init__.py
image_processing_clpe/processing/__init__.py
image_processing_clpe/processing/combination.py
image_processing_clpe/processing/transformation.py
image_processing_clpe/utils/__init__.py
image_processing_clpe/utils/io.py
image_processing_clpe/utils/plot.py
image_processing_clpe-0.0.1.dist-info/METADATA
image_processing_clpe-0.0.1.dist-info/WHEEL
image_processing_clpe-0.0.1.dist-info/top_level.txt
image_processing_clpe-0.0.1.dist-info/RECORD
