Metadata-Version: 2.1
Name: image-processing-clpe
Version: 0.0.1
Summary: Image Processing Package using Skimage
Home-page: https://github.com/carvalho355/desafiosDIOpython-/tree/main/image-processing-package
Author: Carvalho355
Author-email: carlos.ce355@gmail.com
Requires-Python: >=3.8
Requires-Dist: matplotlib
Requires-Dist: numpy
Requires-Dist: scikit-image (>=0.16.1)
